fondat/postgresql.py
fondat_postgresql-4.1.0.dist-info/LICENSE
fondat_postgresql-4.1.0.dist-info/METADATA
fondat_postgresql-4.1.0.dist-info/WHEEL
fondat_postgresql-4.1.0.dist-info/RECORD
