Metadata-Version: 2.1
Name: fondat-postgresql
Version: 4.1.0
Summary: Fondat module for PostgreSQL.
Home-page: https://github.com/fondat/fondat-postgresql/
License: MIT
Keywords: asgi,framework,resource,openapi
Author: fondat-postgresql authors
Requires-Python: >=3.10,<4.0
Classifier: Development Status :: 5 - Production/Stable
Classifier: Intended Audience :: Developers
Classifier: License :: OSI Approved :: MIT License
Classifier: Programming Language :: Python :: 3
Classifier: Programming Language :: Python :: 3.10
Classifier: Programming Language :: Python :: 3.11
Classifier: Topic :: Software Development :: Libraries :: Application Frameworks
Requires-Dist: asyncpg (>=0.26,<0.27)
Requires-Dist: fondat (>=4.1.4,<5.0.0)
Project-URL: Documentation, https://github.com/fondat/fondat-postgresql/wiki
